Full_Menu/__init__.py
Full_Menu/main.py
Full_Menu/menu.py
Full_Menu/screen.py
Full_Menu/text.py
Full_Menu/theme.py
Full_Menu/Parts/body.py
Full_Menu/Parts/footer.py
Full_Menu/Parts/header.py
Full_Menu/items/function.py
full_menu-0.0.1.dist-info/METADATA
full_menu-0.0.1.dist-info/WHEEL
full_menu-0.0.1.dist-info/licenses/LICENSE
full_menu-0.0.1.dist-info/RECORD
